htmlmerge/__init__.py
htmlmerge/htmlmerge.py
htmlmerge-1.2.7.dist-info/DESCRIPTION.rst
htmlmerge-1.2.7.dist-info/METADATA
htmlmerge-1.2.7.dist-info/RECORD
htmlmerge-1.2.7.dist-info/WHEEL
htmlmerge-1.2.7.dist-info/metadata.json
htmlmerge-1.2.7.dist-info/top_level.txt
