Metadata-Version: 2.0
Name: htmlmerge
Version: 1.2.7
Summary: Merges html files that are created by pdfminer.six using exact option
Home-page: https://github.com/le-sun/htmlmerge
Author: Leo Sun
Author-email: leo.sun@berkeley.edu
License: MIT
Keywords: html merge pdfminer pdfminer.six
Platform: UNKNOWN
Classifier: Development Status :: 4 - Beta
Classifier: Intended Audience :: Developers
Classifier: Topic :: Software Development :: Build Tools
Classifier: License :: OSI Approved :: MIT License
Classifier: Programming Language :: Python :: 2
Classifier: Programming Language :: Python :: 2.7
Classifier: Programming Language :: Python :: 3
Classifier: Programming Language :: Python :: 3.3
Classifier: Programming Language :: Python :: 3.4
Classifier: Programming Language :: Python :: 3.5
Requires-Dist: bs4
Requires-Dist: lxml
